bittrex_websocket/__init__.py
bittrex_websocket/_abc.py
bittrex_websocket/_auxiliary.py
bittrex_websocket/_exceptions.py
bittrex_websocket/_logger.py
bittrex_websocket/_queue_events.py
bittrex_websocket/constants.py
bittrex_websocket/websocket_client.py
bittrex_websocket_aio_pundix-0.0.5.dist-info/LICENSE
bittrex_websocket_aio_pundix-0.0.5.dist-info/METADATA
bittrex_websocket_aio_pundix-0.0.5.dist-info/WHEEL
bittrex_websocket_aio_pundix-0.0.5.dist-info/top_level.txt
bittrex_websocket_aio_pundix-0.0.5.dist-info/RECORD
