Metadata-Version: 2.1
Name: bittrex-websocket-aio-pundix
Version: 0.0.5
Summary: The unofficial Python websocket (AsyncIO) client for the Bittrex Cryptocurrency Exchange
Home-page: https://github.com/lowjiansheng/python-bittrex-websocket-aio
Author: Jian Sheng Low
Author-email: jiansheng@pundix.com
License: MIT
Download-URL: https://github.com/lowjiansheng/python-bittrex-websocket-aio.git
Keywords: bittrex,bittrex-websocket,orderbook,trade,bitcoin,ethereum,BTC,ETH,client,websocket,exchange,crypto,currency,trading,async,aio
Platform: UNKNOWN
Classifier: Development Status :: 3 - Alpha
Classifier: Intended Audience :: Developers
Classifier: Intended Audience :: Financial and Insurance Industry
Classifier: Intended Audience :: Information Technology
Classifier: Topic :: Software Development :: Libraries :: Python Modules
Classifier: License :: OSI Approved :: MIT License
Classifier: Programming Language :: Python :: 3.5
Classifier: Programming Language :: Python :: 3.6
Requires-Dist: websockets (>=6.0)
Requires-Dist: signalr-client-aio (>=0.0.1.6.1)
